redminelib/__init__.py
redminelib/exceptions.py
redminelib/lookups.py
redminelib/resultsets.py
redminelib/utilities.py
redminelib/version.py
redminelib/engines/__init__.py
redminelib/engines/base.py
redminelib/engines/sync.py
redminelib/managers/__init__.py
redminelib/managers/base.py
redminelib/managers/standard.py
redminelib/resources/__init__.py
redminelib/resources/base.py
redminelib/resources/standard.py
python_redmine-2.5.0.dist-info/METADATA
python_redmine-2.5.0.dist-info/WHEEL
python_redmine-2.5.0.dist-info/top_level.txt
python_redmine-2.5.0.dist-info/RECORD
