Metadata-Version: 2.1
Name: python-redmine
Version: 2.5.0
Summary: Library for communicating with a Redmine project management application
Home-page: https://github.com/maxtepkeev/python-redmine
Author: Maxim Tepkeev
Author-email: support@python-redmine.com
License: Apache 2.0
Project-URL: Documentation, https://python-redmine.com
Keywords: redmine redmineup redminecrm redminelib easyredmine
Classifier: Development Status :: 5 - Production/Stable
Classifier: License :: OSI Approved :: Apache Software License
Classifier: Topic :: Software Development :: Libraries :: Python Modules
Classifier: Topic :: Utilities
Classifier: Topic :: Internet :: WWW/HTTP
Classifier: Intended Audience :: Developers
Classifier: Environment :: Console
Classifier: Environment :: Web Environment
Classifier: Operating System :: OS Independent
Classifier: Programming Language :: Python :: 3.7
Classifier: Programming Language :: Python :: 3.8
Classifier: Programming Language :: Python :: 3.9
Classifier: Programming Language :: Python :: 3.10
Classifier: Programming Language :: Python :: 3.11
Classifier: Programming Language :: Python :: 3.12
Classifier: Programming Language :: Python :: 3 :: Only
Classifier: Programming Language :: Python :: Implementation :: CPython
Classifier: Programming Language :: Python :: Implementation :: PyPy
Requires-Python: >=3.7, <4
Requires-Dist: requests>=2.31.0
